factory_trytond/__init__.py
factory_trytond-1.0.0.dist-info/LICENSE
factory_trytond-1.0.0.dist-info/METADATA
factory_trytond-1.0.0.dist-info/WHEEL
factory_trytond-1.0.0.dist-info/top_level.txt
factory_trytond-1.0.0.dist-info/RECORD
