Metadata-Version: 2.1
Name: factory-trytond
Version: 1.0.0
Summary: Factory Boy - Trytond integration
Home-page: https://github.com/calidae/factory-trytond
Author: Calidae
Author-email: dev@calidae.com
License: GPLv3+
Platform: any
Classifier: Development Status :: 4 - Beta
Classifier: Framework :: Tryton
Classifier: Intended Audience :: Developers
Classifier: License :: OSI Approved :: GNU General Public License v3 or later (GPLv3+)
Classifier: Operating System :: OS Independent
Classifier: Programming Language :: Python :: 3
Classifier: Programming Language :: Python :: 3 :: Only
Classifier: Programming Language :: Python :: 3.8
Classifier: Programming Language :: Python :: 3.9
Classifier: Programming Language :: Python :: 3.10
Classifier: Programming Language :: Python :: 3.11
Classifier: Topic :: Software Development :: Testing
Requires-Python: >=3.8
License-File: LICENSE
Requires-Dist: factory-boy
Requires-Dist: trytond
Provides-Extra: tests
Requires-Dist: pytest-trytond ; extra == 'tests'
